pydis_pixels/__init__.py
pydis_pixels/canvas.py
pydis_pixels-0.1.1.dist-info/LICENSE
pydis_pixels-0.1.1.dist-info/METADATA
pydis_pixels-0.1.1.dist-info/WHEEL
pydis_pixels-0.1.1.dist-info/top_level.txt
pydis_pixels-0.1.1.dist-info/RECORD
